mono/__init__.py
mono/types.py
PyMonoBankAPI-0.1.dist-info/METADATA
PyMonoBankAPI-0.1.dist-info/WHEEL
PyMonoBankAPI-0.1.dist-info/top_level.txt
PyMonoBankAPI-0.1.dist-info/RECORD
