Metadata-Version: 2.1
Name: PyMonoBankAPI
Version: 0.1
Summary: simple lib for monobank API:)
Home-page: https://github.com/Tynukua/mono
Author: Tynukua
Author-email: tynuk.ua@gmail.com
License: UNKNOWN
Platform: UNKNOWN
Classifier: Programming Language :: Python :: 3
Classifier: License :: OSI Approved :: MIT License
Classifier: Operating System :: OS Independent
Requires-Dist: requests
